fyers_sdk/__init__.py
fyers_sdk/fyersModel.py
fyers_sdk/fyers_logger.py
fyers_sdk/FyersWebsocket/__init__.py
fyers_sdk/FyersWebsocket/data_ws.py
fyers_sdk/FyersWebsocket/defines.py
fyers_sdk/FyersWebsocket/map.json
fyers_sdk/FyersWebsocket/order_ws.py
fyers_sdk-2.1.9.dist-info/LICENSE.txt
fyers_sdk-2.1.9.dist-info/METADATA
fyers_sdk-2.1.9.dist-info/WHEEL
fyers_sdk-2.1.9.dist-info/top_level.txt
fyers_sdk-2.1.9.dist-info/RECORD
