Metadata-Version: 2.1
Name: fyers-sdk
Version: 2.1.9
Summary: Fyers trading APIs.
Home-page: https://github.com/FyersDev/fyers-api-py
Author: Fyers-Tech
Author-email: support@fyers.in
Classifier: Programming Language :: Python :: 3
Classifier: License :: OSI Approved :: MIT License
Classifier: Operating System :: OS Independent
License-File: LICENSE.txt
Requires-Dist: requests (==2.31.0)
Requires-Dist: asyncio (==3.4.3)
Requires-Dist: aiohttp (==3.8.4)
Requires-Dist: aws-lambda-powertools (==1.25.5)
Requires-Dist: websocket-client (==1.6.1)
